structures/__init__.py
python_structures-0.1.3.dist-info/LICENSE
python_structures-0.1.3.dist-info/METADATA
python_structures-0.1.3.dist-info/WHEEL
python_structures-0.1.3.dist-info/top_level.txt
python_structures-0.1.3.dist-info/RECORD
